LICENSE
README.md
setup.py
CVE_2024_27956.egg-info/PKG-INFO
CVE_2024_27956.egg-info/SOURCES.txt
CVE_2024_27956.egg-info/dependency_links.txt
CVE_2024_27956.egg-info/entry_points.txt
CVE_2024_27956.egg-info/requires.txt
CVE_2024_27956.egg-info/top_level.txt
cve202427956/main.py
cve202427956/includes/__init__.py
cve202427956/includes/bot.py
cve202427956/includes/filereader.py
cve202427956/includes/scan.py
cve202427956/includes/writefile.py
cve202427956/utils/__init__.py
cve202427956/utils/configure.py
cve202427956/utils/const.py
cve202427956/utils/helpers.py
cve202427956/utils/status.py